flake8_clean_block.py
flake8_clean_block-0.1.2.dist-info/LICENSE
flake8_clean_block-0.1.2.dist-info/METADATA
flake8_clean_block-0.1.2.dist-info/WHEEL
flake8_clean_block-0.1.2.dist-info/entry_points.txt
flake8_clean_block-0.1.2.dist-info/top_level.txt
flake8_clean_block-0.1.2.dist-info/RECORD
