Metadata-Version: 2.1
Name: flake8-clean-block
Version: 0.1.2
Summary: A flake8 plugin that enforces a blank line after if/for/while/with/try blocks
Home-page: https://github.com/cyyc1/flake8-clean-block
Author: 
Author-email: 
License: MIT
Classifier: License :: OSI Approved :: MIT License
Classifier: Programming Language :: Python :: 3
Classifier: Programming Language :: Python :: 3 :: Only
Classifier: Programming Language :: Python :: Implementation :: CPython
Requires-Python: >=3.8
License-File: LICENSE
